newblackpink/__init__.py
newblackpink/blackpink.otf
newblackpink-1.0.dist-info/METADATA
newblackpink-1.0.dist-info/WHEEL
newblackpink-1.0.dist-info/top_level.txt
newblackpink-1.0.dist-info/RECORD
