Metadata-Version: 2.1
Name: newblackpink
Version: 1.0
Summary: Blackpink Logo Generator
Home-page: https://github.com/PiroHackz/newblackpink
Download-URL: https://github.com/PiroHackz/newblackpink/archive/0.1.tar.gz
Author: Piro Ayush
Author-email: piroayush.tele@gmail.com
License: MIT
Keywords: blackpink,logo,generator
Classifier: Development Status :: 3 - Alpha
Classifier: Intended Audience :: Developers
Classifier: Topic :: Software Development :: Build Tools
Classifier: License :: OSI Approved :: MIT License
Classifier: Programming Language :: Python :: 3.8
Classifier: Programming Language :: Python :: 3.9
Requires-Dist: pillow
